atpbar/__about__.py
atpbar/__init__.py
atpbar/callback.py
atpbar/funcs.py
atpbar/machine.py
atpbar/main.py
atpbar/py.typed
atpbar/presentation/__init__.py
atpbar/presentation/barjupyter.py
atpbar/presentation/bartty.py
atpbar/presentation/base.py
atpbar/presentation/create.py
atpbar/presentation/txtprint.py
atpbar/presentation/detect/__init__.py
atpbar/presentation/detect/jupy.py
atpbar/presentation/detect/spy.py
atpbar/progress_report/__init__.py
atpbar/progress_report/pickup.py
atpbar/progress_report/report.py
atpbar/progress_report/reporter.py
atpbar/stream/__init__.py
atpbar/stream/output.py
atpbar/stream/pickup.py
atpbar/stream/redirect.py
atpbar/stream/type.py
atpbar-2.0.7.dist-info/METADATA
atpbar-2.0.7.dist-info/WHEEL
atpbar-2.0.7.dist-info/licenses/LICENSE
atpbar-2.0.7.dist-info/RECORD
