Metadata-Version: 2.4
Name: atpbar
Version: 2.0.7
Summary: Progress bars for threading and multiprocessing tasks
Project-URL: Homepage, https://github.com/alphatwirl/atpbar
Author-email: Tai Sakuma <tai.sakuma@gmail.com>
License-Expression: MIT
License-File: LICENSE
Classifier: Development Status :: 5 - Production/Stable
Classifier: Intended Audience :: Developers
Classifier: Intended Audience :: End Users/Desktop
Classifier: License :: OSI Approved :: MIT License
Classifier: Programming Language :: Python
Classifier: Programming Language :: Python :: 3.10
Classifier: Programming Language :: Python :: 3.11
Classifier: Programming Language :: Python :: 3.12
Classifier: Programming Language :: Python :: 3.13
Classifier: Programming Language :: Python :: 3.14
Requires-Python: >=3.10
Requires-Dist: typing-extensions>=4.12; python_version < '3.10'
Provides-Extra: doc
Requires-Dist: mkdocs-material>=9.5; extra == 'doc'
Requires-Dist: pymdown-extensions>=10.8; extra == 'doc'
Provides-Extra: jupyter
Requires-Dist: ipywidgets>=8.1; extra == 'jupyter'
Provides-Extra: tests
Requires-Dist: hypothesis>=6.102.6; extra == 'tests'
Requires-Dist: pytest-console-scripts>=1.4; extra == 'tests'
Requires-Dist: pytest-cov>=5.0; extra == 'tests'
Requires-Dist: pytest>=8.2; extra == 'tests'
